<?xml version="1.0" encoding="utf-8" ?>
<dwsync>
<file name="pappa_boat.jpg" server="elmgren.nu/public_html/" local="127674946200000000" remote="129377691600000000" />
<file name="pappa_boat_thumb.jpg" server="elmgren.nu/public_html/" local="127674946200000000" remote="129377691600000000" />
<file name="stef_jess_cold.jpg" server="elmgren.nu/public_html/" local="127674946200000000" remote="129377691600000000" />
<file name="stef_jess_cold_thumb.jpg" server="elmgren.nu/public_html/" local="127674946200000000" remote="129377691600000000" />
<file name="brasa.jpg" server="elmgren.nu/public_html/" local="127674946200000000" remote="129377691600000000" />
<file name="brasa_thumb.jpg" server="elmgren.nu/public_html/" local="127674946200000000" remote="129377691600000000" />
<file name="pappa_varvet.jpg" server="elmgren.nu/public_html/" local="127674946200000000" remote="129377691600000000" />
<file name="pappa_varvet_thumb.jpg" server="elmgren.nu/public_html/" local="127674946200000000" remote="129377691600000000" />
<file name="stefan_boat.jpg" server="elmgren.nu/public_html/" local="127674946200000000" remote="129377691600000000" />
<file name="stefan_boat_thumb.jpg" server="elmgren.nu/public_html/" local="127674946200000000" remote="129377691600000000" />
<file name="jess_mick.jpg" server="elmgren.nu/public_html/" local="127674946200000000" remote="129377691600000000" />
<file name="jess_mick_thumb.jpg" server="elmgren.nu/public_html/" local="127674946200000000" remote="129377691600000000" />
<file name="friskt.jpg" server="elmgren.nu/public_html/" local="127674946200000000" remote="129377691600000000" />
<file name="friskt_thumb.jpg" server="elmgren.nu/public_html/" local="127674946200000000" remote="129377691600000000" />
<file name="dan_boat_96.jpg" server="elmgren.nu/public_html/" local="127674946200000000" remote="129377691600000000" />
<file name="dan_boat_96_thumb.jpg" server="elmgren.nu/public_html/" local="127674946200000000" remote="129377691600000000" />
<file name="boin_boat_96.jpg" server="elmgren.nu/public_html/" local="127674946200000000" remote="129377691600000000" />
<file name="boin_boat_96_thumb.jpg" server="elmgren.nu/public_html/" local="127674946200000000" remote="129377691600000000" />
<file name="stef_eriks_96.jpg" server="elmgren.nu/public_html/" local="127674946200000000" remote="129377691600000000" />
<file name="stef_eriks_96_thumb.jpg" server="elmgren.nu/public_html/" local="127674946200000000" remote="129377691600000000" />
<file name="scarecrow.jpg" server="elmgren.nu/public_html/" local="127674946200000000" remote="129377691600000000" />
<file name="scarecrow_thumb.jpg" server="elmgren.nu/public_html/" local="127674946200000000" remote="129377691600000000" />
<file name="stefan_fyller_25.jpg" server="elmgren.nu/public_html/" local="127674946200000000" remote="129377691600000000" />
<file name="stefan_fyller_25_th.jpg" server="elmgren.nu/public_html/" local="127674946200000000" remote="129377691600000000" />
<file name="stefan_bcn_thmb.jpg" server="elmgren.nu/public_html/" local="127670599800000000" remote="129377691600000000" />
<file name="lifta_mot_basel.jpg" server="elmgren.nu/public_html/" local="127670599800000000" remote="129377691600000000" />
<file name="lifta_mot_basel_thmb.jpg" server="elmgren.nu/public_html/" local="127670599800000000" remote="129377691600000000" />
<file name="lift_mobile_home.jpg" server="elmgren.nu/public_html/" local="127670599800000000" remote="129377691600000000" />
<file name="lift_mobile_home_thmb.jpg" server="elmgren.nu/public_html/" local="127670599800000000" remote="129377691600000000" />
<file name="stefan_jonas_liftar.jpg" server="elmgren.nu/public_html/" local="127674946200000000" remote="129377691600000000" />
<file name="stefan_jonas_liftar_thmb.jpg" server="elmgren.nu/public_html/" local="127674946200000000" remote="129377691600000000" />
<file name="stefan_bcn.jpg" server="elmgren.nu/public_html/" local="127670599800000000" remote="129377691600000000" />
<file name="johann_stefan_anna_cadiz_95.jpg" server="elmgren.nu/public_html/" local="127674946200000000" remote="129377691600000000" />
<file name="boi_ste_jul.jpg" server="elmgren.nu/public_html/" local="127674946200000000" remote="129377691600000000" />
<file name="daniel_stefan_bcn_jan_93.jpg" server="elmgren.nu/public_html/" local="127674946200000000" remote="129377016000000000" />
<file name="johann_stefan_anna_cadiz_95_thmb.jpg" server="elmgren.nu/public_html/" local="127674946200000000" remote="129377016000000000" />
<file name="boi_ste_jul_thmb.jpg" server="elmgren.nu/public_html/" local="127674946200000000" remote="129377016000000000" />
<file name="daniel_stefan_bcn_jan_93_thmb.jpg" server="elmgren.nu/public_html/" local="127674946200000000" remote="129377016000000000" />
<file name="ste_grott_nerja.jpg" server="elmgren.nu/public_html/" local="129891823020000000" remote="129891826200000000" />
<file name="ste_grott_nerja_thmb.jpg" server="elmgren.nu/public_html/" local="129891823640000000" remote="129891096000000000" />
<file name="bir_fuengirola.jpg" server="elmgren.nu/public_html/" local="129891831160000000" remote="129891835800000000" />
<file name="bir_fuengirola_thmb.jpg" server="elmgren.nu/public_html/" local="129891831840000000" remote="129891835800000000" />
<file name="marian_fuengirola.jpg" server="elmgren.nu/public_html/" local="129891834300000000" remote="129891835800000000" />
<file name="marian_fuengirola_thmb.jpg" server="elmgren.nu/public_html/" local="129891834760000000" remote="129891835800000000" />
</dwsync>